README.md
setup.py
efb_caiyun_weather_slave/__init__.py
efb_caiyun_weather_slave/__version__.py
efb_caiyun_weather_slave.egg-info/PKG-INFO
efb_caiyun_weather_slave.egg-info/SOURCES.txt
efb_caiyun_weather_slave.egg-info/dependency_links.txt
efb_caiyun_weather_slave.egg-info/entry_points.txt
efb_caiyun_weather_slave.egg-info/requires.txt
efb_caiyun_weather_slave.egg-info/top_level.txt