Metadata-Version: 2.1
Name: efb-caiyun-weather-slave
Version: 0.0.1.dev4
Summary: EFB CaiYun Weather Slave Channel
Home-page: https://github.com/sunziping2016/efb-caiyun-weather-slave
Author: Sun Ziping
Author-email: sunziping2016@gmail.com
License: GPLv3
Keywords: ehforwarderbot,EH Forwarder Bot,EH Forwarder Bot Slave Channel,weather,CaiYun
Platform: UNKNOWN
Classifier: Development Status :: 3 - Alpha
Classifier: License :: OSI Approved :: GNU General Public License v3 (GPLv3)
Classifier: Intended Audience :: Developers
Classifier: Intended Audience :: End Users/Desktop
Classifier: Programming Language :: Python :: 3 :: Only
Classifier: Programming Language :: Python :: 3.6
Classifier: Programming Language :: Python :: 3.7
Classifier: Topic :: Communications :: Chat
Classifier: Topic :: Utilities
Requires-Python: >=3.6
